pyhead/__init__.py
pyhead/__version__.py
pyhead/_cli.py
pyhead/_helpers.py
pyhead/elements/__init__.py
pyhead/elements/application_name.py
pyhead/elements/base.py
pyhead/elements/charset.py
pyhead/elements/content_security_policy.py
pyhead/elements/description.py
pyhead/elements/favicon.py
pyhead/elements/format_detection.py
pyhead/elements/geo_position.py
pyhead/elements/google.py
pyhead/elements/keywords.py
pyhead/elements/link.py
pyhead/elements/meta.py
pyhead/elements/open_graph_website.py
pyhead/elements/page.py
pyhead/elements/referrer_policy.py
pyhead/elements/robots.py
pyhead/elements/script.py
pyhead/elements/social_media_card.py
pyhead/elements/stylesheet.py
pyhead/elements/theme_color.py
pyhead/elements/title.py
pyhead/elements/twitter_card.py
pyhead/elements/verification.py
pyhead/flask/__init__.py
pyhead/protocols/__init__.py
pyhead-5.3.1.dist-info/entry_points.txt
pyhead-5.3.1.dist-info/licenses/LICENSE
pyhead-5.3.1.dist-info/WHEEL
pyhead-5.3.1.dist-info/METADATA
pyhead-5.3.1.dist-info/RECORD
