Metadata-Version: 2.4
Name: pyhead
Version: 5.3.1
Summary: A simple python package to generate HTML head tags.
Author-email: David Carmichael <david@uilix.com>
Requires-Python: >=3.7
Classifier: License :: OSI Approved :: MIT License
License-File: LICENSE
Requires-Dist: MarkupSafe >= 2.1.3
Requires-Dist: click >= 8.1.7
Project-URL: Home, https://github.com/CheeseCake87/pyhead
